pyvoro2/__init__.py
pyvoro2/_core.cp310-win_amd64.pyd
pyvoro2/api.py
pyvoro2/domains.py
pyvoro2/planes.py
pyvoro2-0.1.0.dist-info/METADATA
pyvoro2-0.1.0.dist-info/WHEEL
pyvoro2-0.1.0.dist-info/licenses/LICENSE.md
pyvoro2-0.1.0.dist-info/RECORD
