Metadata-Version: 2.2
Name: pyvoro2
Version: 0.1.0
Summary: Python bindings for Voro++ with plane-fraction policies for Voronoi tessellation.
Author: Ivan Yu. Chernyshov
License: MIT License
Classifier: Development Status :: 3 - Alpha
Classifier: Intended Audience :: Science/Research
Classifier: Topic :: Scientific/Engineering :: Chemistry
Classifier: Topic :: Scientific/Engineering :: Physics
Classifier: License :: OSI Approved :: MIT License
Classifier: Operating System :: OS Independent
Classifier: Programming Language :: Python :: 3
Classifier: Programming Language :: Python :: 3 :: Only
Classifier: Programming Language :: Python :: 3.10
Classifier: Programming Language :: Python :: 3.11
Classifier: Programming Language :: Python :: 3.12
Classifier: Programming Language :: C++
Project-URL: Homepage, https://github.com/IvanChernyshov/pyvoro2
Project-URL: Repository, https://github.com/IvanChernyshov/pyvoro2
Project-URL: Issues, https://github.com/IvanChernyshov/pyvoro2/issues
Requires-Python: >=3.10
Requires-Dist: numpy<2,>=1.23; python_version < "3.11"
Requires-Dist: numpy<3,>=1.23; python_version >= "3.11"
Provides-Extra: test
Requires-Dist: pytest; extra == "test"
